{"code":0,"data":[{"cid":2346,"deleted":false,"image_metadata":{},"is_dz":false,"name":"Alice","permissions":["report"],"pid":343,"reply_to":-1,"tag":null,"text":"资瓷","timestamp":1592713540,"type":"text","url":""},{"cid":2958,"deleted":false,"image_metadata":{},"is_dz":false,"name":"Bob","permissions":["report"],"pid":343,"reply_to":-1,"tag":null,"text":"TG群是什么意思？以及链接打不开啊\n","timestamp":1592719721,"type":"text","url":""},{"cid":2969,"deleted":false,"image_metadata":{},"is_dz":false,"name":"Carol","permissions":["report"],"pid":343,"reply_to":-1,"tag":null,"text":"啊 我建议直接用已有的清华TG群吧 有清华身份验证的\nhttps://t.me/tsinghuaWater","timestamp":1592719853,"type":"text","url":""},{"cid":2981,"deleted":false,"image_metadata":{},"is_dz":false,"name":"Dave","permissions":["report"],"pid":343,"reply_to":-1,"tag":null,"text":"Re Bob: 请先科学上网","timestamp":1592720000,"type":"text","url":""}],"post":{"attention":false,"deleted":false,"image_metadata":{},"likenum":8,"permissions":["report","fold"],"pid":343,"reply":4,"tag":null,"text":"为了避免洞被贵校迅速橄榄，我先放一个非官方的tg群在这：https://t.me/joinchat/JdqxvR0ljRmvYFIeCBfMxg","timestamp":1592698552,"type":"text","updated_at":1606782583,"url":"","vote":{}}}