{"code":0,"data":[{"cid":2184,"deleted":false,"image_metadata":{},"is_dz":false,"name":"Alice","permissions":["report"],"pid":632,"reply_to":-1,"tag":null,"text":"蹲","timestamp":1592712375,"type":"text","url":""},{"cid":2206,"deleted":false,"image_metadata":{},"is_dz":false,"name":"Bob","permissions":["report"],"pid":632,"reply_to":-1,"tag":null,"text":"插眼","timestamp":1592712449,"type":"text","url":""},{"cid":2288,"deleted":false,"image_metadata":{},"is_dz":false,"name":"Carol","permissions":["report"],"pid":632,"reply_to":-1,"tag":null,"text":"插眼","timestamp":1592713064,"type":"text","url":""},{"cid":2325,"deleted":false,"image_metadata":{},"is_dz":false,"name":"Dave","permissions":["report"],"pid":632,"reply_to":-1,"tag":null,"text":"插眼","timestamp":1592713360,"type":"text","url":""},{"cid":2356,"deleted":false,"image_metadata":{},"is_dz":false,"name":"Eve","permissions":["report"],"pid":632,"reply_to":-1,"tag":null,"text":"荤的还是素的，荤的大家都放不开，素的大家也放不开，现在情况就是这么个情况。 ","timestamp":1592713599,"type":"text","url":""},{"cid":2390,"deleted":false,"image_metadata":{},"is_dz":true,"name":"洞主","permissions":["report"],"pid":632,"reply_to":-1,"tag":null,"text":"Re Eve: 素的就可，只是想谈恋爱（","timestamp":1592713816,"type":"text","url":""},{"cid":2526,"deleted":false,"image_metadata":{},"is_dz":false,"name":"Eve","permissions":["report"],"pid":632,"reply_to":-1,"tag":null,"text":"Re 洞主: 那走清华帮吧，素的不需要匿名，发个任务很多群的。","timestamp":1592714519,"type":"text","url":""},{"cid":2755,"deleted":false,"image_metadata":{},"is_dz":true,"name":"洞主","permissions":["report"],"pid":632,"reply_to":-1,"tag":null,"text":"Re Eve: 感谢指路","timestamp":1592716199,"type":"text","url":""},{"cid":2926,"deleted":false,"image_metadata":{},"is_dz":false,"name":"Francis","permissions":["report"],"pid":632,"reply_to":-1,"tag":null,"text":"Re Eve: 清华帮是指水木帮吗？","timestamp":1592719285,"type":"text","url":""},{"cid":3529,"deleted":false,"image_metadata":{},"is_dz":true,"name":"洞主","permissions":["report"],"pid":632,"reply_to":-1,"tag":null,"text":"Re Francis: 是的","timestamp":1592724648,"type":"text","url":""}],"post":{"attention":false,"deleted":false,"image_metadata":{},"likenum":7,"permissions":["report","fold"],"pid":632,"reply":10,"tag":null,"text":"求问你清有相亲群吗，想脱单qwq","timestamp":1592712358,"type":"text","updated_at":1606782581,"url":"","vote":{}}}