{"code":0,"data":[{"cid":6199,"deleted":false,"image_metadata":{},"is_dz":false,"name":"Alice","permissions":["report"],"pid":1313,"reply_to":-1,"tag":null,"text":"建议都去做fwz毛概给的那个测试","timestamp":1592744608,"type":"text","url":""},{"cid":6201,"deleted":false,"image_metadata":{},"is_dz":false,"name":"Bob","permissions":["report"],"pid":1313,"reply_to":-1,"tag":null,"text":"Re Alice: 求链接","timestamp":1592744629,"type":"text","url":""},{"cid":6259,"deleted":false,"image_metadata":{},"is_dz":false,"name":"Carol","permissions":["report"],"pid":1313,"reply_to":-1,"tag":null,"text":"politicalcompass.org，不过还是西方的那一套理论","timestamp":1592745075,"type":"text","url":""},{"cid":6271,"deleted":false,"image_metadata":{},"is_dz":false,"name":"Dave","permissions":["report"],"pid":1313,"reply_to":-1,"tag":null,"text":"原教旨马克思主义者(自由左) \n赶快建立无产阶级民主专政，gkd \n严防再次变成长期“先锋队”专政\n时刻不忘消灭阶级、消灭国家的最终目的","timestamp":1592745150,"type":"text","url":""},{"cid":6275,"deleted":false,"image_metadata":{},"is_dz":false,"name":"Eve","permissions":["report"],"pid":1313,"reply_to":-1,"tag":null,"text":"原教旨马","timestamp":1592745158,"type":"text","url":""},{"cid":6281,"deleted":false,"image_metadata":{},"is_dz":false,"name":"Eve","permissions":["report"],"pid":1313,"reply_to":-1,"tag":null,"text":"Re Dave: 消灭资法权！","timestamp":1592745189,"type":"text","url":""},{"cid":6328,"deleted":false,"image_metadata":{},"is_dz":false,"name":"Francis","permissions":["report"],"pid":1313,"reply_to":-1,"tag":null,"text":"建议这个https://www.politiscales.net/","timestamp":1592745476,"type":"text","url":""},{"cid":6335,"deleted":false,"image_metadata":{},"is_dz":false,"name":"Grace","permissions":["report"],"pid":1313,"reply_to":-1,"tag":null,"text":"唯....唯心主义怎么办，还是主观唯心","timestamp":1592745505,"type":"text","url":""},{"cid":6345,"deleted":false,"image_metadata":{},"is_dz":false,"name":"Hans","permissions":["report"],"pid":1313,"reply_to":-1,"tag":null,"text":"肉身温和右派，精神温和左派。\n日常生活大事偏左派小事偏右派。\n感觉小市民阶级大都就是我这样（？）也可能他们连精神上的左都不愿意沾染，精神资本家就很可怕了","timestamp":1592745535,"type":"text","url":""},{"cid":6355,"deleted":false,"image_metadata":{},"is_dz":false,"name":"Carol","permissions":["report"],"pid":1313,"reply_to":-1,"tag":null,"text":"Re Grace: 这是zz倾向吗","timestamp":1592745609,"type":"text","url":""},{"cid":6365,"deleted":false,"image_metadata":{},"is_dz":false,"name":"Carol","permissions":["report"],"pid":1313,"reply_to":-1,"tag":null,"text":"Re Hans: 「我真的有一头牛」","timestamp":1592745667,"type":"text","url":""},{"cid":6468,"deleted":false,"image_metadata":{},"is_dz":false,"name":"Isabella","permissions":["report"],"pid":1313,"reply_to":-1,"tag":null,"text":"爷是左派","timestamp":1592746252,"type":"text","url":""},{"cid":6568,"deleted":false,"image_metadata":{},"is_dz":false,"name":"Grace","permissions":["report"],"pid":1313,"reply_to":-1,"tag":null,"text":"Re Carol: 我不知道政教合一算左中右什么","timestamp":1592746740,"type":"text","url":""},{"cid":6586,"deleted":false,"image_metadata":{},"is_dz":false,"name":"Jason","permissions":["report"],"pid":1313,"reply_to":-1,"tag":null,"text":"Re Alice: 那个太粗糙了","timestamp":1592746820,"type":"text","url":""},{"cid":6638,"deleted":false,"image_metadata":{},"is_dz":false,"name":"Kate","permissions":["report"],"pid":1313,"reply_to":-1,"tag":null,"text":"自由左","timestamp":1592747081,"type":"text","url":""}],"post":{"attention":false,"deleted":false,"image_metadata":{},"likenum":8,"permissions":["report","fold"],"pid":1313,"reply":15,"tag":null,"text":"冲个塔   大家zz倾向都是啥啊？\n我先来  ←壬偏保守","timestamp":1592744571,"type":"text","updated_at":1606782584,"url":"","vote":{}}}