{"code":0,"data":[{"cid":9251,"deleted":false,"image_metadata":{},"is_dz":false,"name":"Alice","permissions":["report"],"pid":1755,"reply_to":-1,"tag":null,"text":"正版office不好吗","timestamp":1592762488,"type":"text","url":""},{"cid":9252,"deleted":false,"image_metadata":{},"is_dz":false,"name":"Bob","permissions":["report"],"pid":1755,"reply_to":-1,"tag":null,"text":"我喜欢word？","timestamp":1592762497,"type":"text","url":""},{"cid":9259,"deleted":false,"image_metadata":{},"is_dz":false,"name":"Carol","permissions":["report"],"pid":1755,"reply_to":-1,"tag":null,"text":"我喜欢keynote","timestamp":1592762564,"type":"text","url":""},{"cid":9264,"deleted":false,"image_metadata":{},"is_dz":false,"name":"Dave","permissions":["report"],"pid":1755,"reply_to":-1,"tag":null,"text":"都给爷libreoffice让开(狗头","timestamp":1592762585,"type":"text","url":""},{"cid":9523,"deleted":false,"image_metadata":{},"is_dz":false,"name":"Eve","permissions":["report"],"pid":1755,"reply_to":-1,"tag":null,"text":"给爷整一个latex","timestamp":1592765627,"type":"text","url":""},{"cid":9544,"deleted":false,"image_metadata":{},"is_dz":false,"name":"Francis","permissions":["report"],"pid":1755,"reply_to":-1,"tag":null,"text":"Re Alice: 我会说wps比微软word更早出生吗","timestamp":1592766226,"type":"text","url":""}],"post":{"attention":false,"deleted":false,"image_metadata":{},"likenum":6,"permissions":["report","fold"],"pid":1755,"reply":6,"tag":null,"text":"我喜欢wps！！！","timestamp":1592762466,"type":"text","updated_at":1606782583,"url":"","vote":{}}}