{"code":0,"data":[{"cid":15301,"deleted":false,"image_metadata":{},"is_dz":false,"name":"Alice","permissions":["report"],"pid":2668,"reply_to":-1,"tag":null,"text":"演技太尬","timestamp":1592823703,"type":"text","url":""},{"cid":15340,"deleted":false,"image_metadata":{},"is_dz":false,"name":"Bob","permissions":["report"],"pid":2668,"reply_to":-1,"tag":null,"text":"长相其实一般 有点刻薄相 陈芊芊剧本太无脑了 尤其前段时间上热搜的那个编剧续写的番外 尬出一湖春水 采访很机灵 比xz机灵多了（非粉圈不拉踩 vlog风格虽然比一般高级但不太喜欢 总觉得是不太真诚的人","timestamp":1592823844,"type":"text","url":""}],"post":{"attention":false,"deleted":false,"image_metadata":{},"likenum":2,"permissions":["report","fold"],"pid":2668,"reply":2,"tag":null,"text":"大家喜欢丁禹兮吗","timestamp":1592823619,"type":"text","updated_at":1606782584,"url":"","vote":{}}}