{"code":0,"data":[{"cid":22779,"deleted":false,"image_metadata":{},"is_dz":false,"name":"Alice","permissions":["report"],"pid":3817,"reply_to":-1,"tag":null,"text":"？","timestamp":1592891254,"type":"text","url":""},{"cid":22804,"deleted":false,"image_metadata":{},"is_dz":false,"name":"Bob","permissions":["report"],"pid":3817,"reply_to":-1,"tag":null,"text":"？","timestamp":1592891319,"type":"text","url":""},{"cid":22826,"deleted":false,"image_metadata":{},"is_dz":false,"name":"Carol","permissions":["report"],"pid":3817,"reply_to":-1,"tag":null,"text":"没有？","timestamp":1592891386,"type":"text","url":""},{"cid":22870,"deleted":false,"image_metadata":{},"is_dz":false,"name":"Dave","permissions":["report"],"pid":3817,"reply_to":-1,"tag":null,"text":"？","timestamp":1592891536,"type":"text","url":""},{"cid":22871,"deleted":false,"image_metadata":{},"is_dz":false,"name":"Eve","permissions":["report"],"pid":3817,"reply_to":-1,"tag":null,"text":"lgbt是固有属性，yp是行为选择，不过在讨论中本质上还是一回事，就是在遇见异己小众且非涉我的观点时，讨论者应该采取什么态度。","timestamp":1592891537,"type":"text","url":""},{"cid":22898,"deleted":false,"image_metadata":{},"is_dz":false,"name":"Francis","permissions":["report"],"pid":3817,"reply_to":-1,"tag":null,"text":"相似：都不吃人，但都有少部分人出来搞糊整个群体（","timestamp":1592891616,"type":"text","url":""}],"post":{"attention":false,"deleted":false,"image_metadata":{},"likenum":4,"permissions":["report","fold"],"pid":3817,"reply":6,"tag":null,"text":"#3767 论LGBT和YP的相似与不同","timestamp":1592891175,"type":"text","updated_at":1606782583,"url":"","vote":{}}}