{"code":0,"data":[{"cid":24357,"deleted":false,"image_metadata":{},"is_dz":false,"name":"Alice","permissions":["report"],"pid":4076,"reply_to":-1,"tag":null,"text":"默默等DL国服","timestamp":1592898765,"type":"text","url":""}],"post":{"attention":false,"deleted":false,"image_metadata":{"h":250,"w":220},"likenum":1,"permissions":["report","fold"],"pid":4076,"reply":1,"tag":null,"text":"啊这","timestamp":1592898465,"type":"image","updated_at":1606782584,"url":"ms/ms5untswm4sbhgupalxbmwgk5vqmslgk.jpeg","vote":{}}}