{"code":0,"data":[{"cid":41118,"deleted":false,"image_metadata":{},"is_dz":false,"name":"Alice","permissions":["report"],"pid":6750,"reply_to":-1,"tag":null,"text":"开通校友邮箱，把邮件和通讯录搬过来。毕业离校了清华邮箱用不了了，只能保留6个月的自动转发功能。","timestamp":1593089703,"type":"text","url":""},{"cid":41204,"deleted":false,"image_metadata":{},"is_dz":true,"name":"洞主","permissions":["report"],"pid":6750,"reply_to":-1,"tag":null,"text":"Re Alice: 看来不能到处都用清华邮箱注册了QAQ 谢谢你！","timestamp":1593090596,"type":"text","url":""}],"post":{"attention":false,"deleted":false,"image_metadata":{},"likenum":2,"permissions":["report","fold"],"pid":6750,"reply":2,"tag":null,"text":"清华邮箱毕业后还能用吗","timestamp":1593089431,"type":"text","updated_at":1606782585,"url":"","vote":{}}}