{"code":0,"data":[{"cid":59569,"deleted":false,"image_metadata":{},"is_dz":false,"name":"Alice","permissions":["report"],"pid":10165,"reply_to":-1,"tag":null,"text":"蹲\n","timestamp":1593352837,"type":"text","url":""},{"cid":59574,"deleted":false,"image_metadata":{},"is_dz":false,"name":"Bob","permissions":["report"],"pid":10165,"reply_to":-1,"tag":null,"text":"在家考啊","timestamp":1593352921,"type":"text","url":""}],"post":{"attention":false,"deleted":false,"image_metadata":{},"likenum":3,"permissions":["report","fold"],"pid":10165,"reply":2,"tag":null,"text":"七字班朋友现在考不上托福gre还出国吗","timestamp":1593352149,"type":"text","updated_at":1606782588,"url":"","vote":{}}}