{"code":0,"data":[{"cid":73618,"deleted":false,"image_metadata":{},"is_dz":false,"name":"Alice","permissions":["report"],"pid":12559,"reply_to":-1,"tag":null,"text":"滋磁","timestamp":1593692416,"type":"text","url":""},{"cid":73621,"deleted":false,"image_metadata":{},"is_dz":false,"name":"Bob","permissions":["report"],"pid":12559,"reply_to":-1,"tag":null,"text":"附议","timestamp":1593692430,"type":"text","url":""},{"cid":73712,"deleted":false,"image_metadata":{},"is_dz":false,"name":"Carol","permissions":["report"],"pid":12559,"reply_to":-1,"tag":null,"text":"+1\n","timestamp":1593694892,"type":"text","url":""},{"cid":73738,"deleted":false,"image_metadata":{},"is_dz":false,"name":"Dave","permissions":["report"],"pid":12559,"reply_to":-1,"tag":null,"text":"+1","timestamp":1593695594,"type":"text","url":""},{"cid":73763,"deleted":false,"image_metadata":{},"is_dz":false,"name":"Eve","permissions":["report"],"pid":12559,"reply_to":-1,"tag":null,"text":"+1","timestamp":1593696174,"type":"text","url":""},{"cid":73783,"deleted":false,"image_metadata":{},"is_dz":false,"name":"Francis","permissions":["report"],"pid":12559,"reply_to":-1,"tag":null,"text":"+1","timestamp":1593696755,"type":"text","url":""},{"cid":73802,"deleted":false,"image_metadata":{},"is_dz":false,"name":"Grace","permissions":["report"],"pid":12559,"reply_to":-1,"tag":null,"text":"+1","timestamp":1593696995,"type":"text","url":""},{"cid":73815,"deleted":false,"image_metadata":{},"is_dz":false,"name":"Hans","permissions":["report"],"pid":12559,"reply_to":-1,"tag":null,"text":"+1","timestamp":1593697132,"type":"text","url":""},{"cid":73817,"deleted":false,"image_metadata":{},"is_dz":false,"name":"Isabella","permissions":["report"],"pid":12559,"reply_to":-1,"tag":null,"text":"+1","timestamp":1593697186,"type":"text","url":""}],"post":{"attention":false,"deleted":false,"image_metadata":{},"likenum":6,"permissions":["report","fold"],"pid":12559,"reply":9,"tag":null,"text":"明天要不要新加一个tag？\n叫#成绩相关#","timestamp":1593692394,"type":"text","updated_at":1606782588,"url":"","vote":{}}}