{"code":0,"data":[{"cid":74520,"deleted":false,"image_metadata":{},"is_dz":false,"name":"Alice","permissions":["report"],"pid":12730,"reply_to":-1,"tag":null,"text":"插眼 到时候我躲着走","timestamp":1593707656,"type":"text","url":""},{"cid":74526,"deleted":false,"image_metadata":{},"is_dz":false,"name":"Bob","permissions":["report"],"pid":12730,"reply_to":-1,"tag":null,"text":"同Alice","timestamp":1593707735,"type":"text","url":""},{"cid":74928,"deleted":false,"image_metadata":{},"is_dz":false,"name":"Carol","permissions":["report"],"pid":12730,"reply_to":-1,"tag":null,"text":"插眼，不同Alice和Bob","timestamp":1593732718,"type":"text","url":""},{"cid":75172,"deleted":false,"image_metadata":{},"is_dz":false,"name":"Dave","permissions":["report"],"pid":12730,"reply_to":-1,"tag":null,"text":" 插眼，不同Alice和Bob，Carol","timestamp":1593738791,"type":"text","url":""},{"cid":75666,"deleted":false,"image_metadata":{},"is_dz":false,"name":"Eve","permissions":["report"],"pid":12730,"reply_to":-1,"tag":null,"text":"宿舍就可以。室友方便","timestamp":1593746256,"type":"text","url":""}],"post":{"attention":false,"deleted":false,"image_metadata":{},"likenum":2,"permissions":["report","fold"],"pid":12730,"reply":5,"tag":"性相关","text":"性相关\n男男在学校yp都去什么地方呀","timestamp":1593707499,"type":"text","updated_at":1606782588,"url":"","vote":{}}}