{"code":0,"data":[{"cid":543201,"deleted":false,"image_metadata":{},"is_dz":false,"name":"Alice","permissions":["report"],"pid":113289,"reply_to":-1,"tag":null,"text":"为什么要聊呢？","timestamp":1605110186,"type":"text","url":""},{"cid":543221,"deleted":false,"image_metadata":{},"is_dz":false,"name":"Bob","permissions":["report"],"pid":113289,"reply_to":-1,"tag":null,"text":"因为都觉得自己的大","timestamp":1605110405,"type":"text","url":""},{"cid":543517,"deleted":false,"image_metadata":{},"is_dz":false,"name":"Carol","permissions":["report"],"pid":113289,"reply_to":-1,"tag":null,"text":"cz就断 习惯了害","timestamp":1605114463,"type":"text","url":""},{"cid":543674,"deleted":false,"image_metadata":{},"is_dz":false,"name":"Dave","permissions":["report"],"pid":113289,"reply_to":-1,"tag":null,"text":"Re Carol: 断了可还行","timestamp":1605116511,"type":"text","url":""}],"post":{"attention":false,"deleted":false,"image_metadata":{},"likenum":1,"permissions":["report","fold"],"pid":113289,"reply":4,"tag":"性相关","text":"#性相关\n为什么没有人讨论短丁丁羞耻呢","timestamp":1605110105,"type":"text","updated_at":1606782642,"url":"","vote":{}}}