{"code":0,"data":[{"cid":543489,"deleted":false,"image_metadata":{},"is_dz":false,"name":"Alice","permissions":["report"],"pid":113335,"reply_to":-1,"tag":null,"text":"世另我","timestamp":1605113996,"type":"text","url":""},{"cid":543664,"deleted":false,"image_metadata":{},"is_dz":false,"name":"Bob","permissions":["report"],"pid":113335,"reply_to":-1,"tag":null,"text":"我们在一起吧。。","timestamp":1605116291,"type":"text","url":""},{"cid":543714,"deleted":false,"image_metadata":{},"is_dz":false,"name":"Carol","permissions":["report"],"pid":113335,"reply_to":-1,"tag":null,"text":"浪漫和平淡冲突嘛。。个人向往两个人安安静静天长日久，甜蜜的浪漫流淌在岁月中（意淫一下然后呜呜呜","timestamp":1605117295,"type":"text","url":""}],"post":{"attention":false,"deleted":false,"image_metadata":{},"likenum":1,"permissions":["report","fold"],"pid":113335,"reply":3,"tag":null,"text":"又想平平淡淡的又有点渴望浪漫\n好矛盾啊","timestamp":1605113449,"type":"text","updated_at":1606782643,"url":"","vote":{}}}