{"code":0,"data":[{"cid":545794,"deleted":false,"image_metadata":{},"is_dz":false,"name":"Alice","permissions":["report"],"pid":113747,"reply_to":-1,"tag":null,"text":"快快快，介错","timestamp":1605171055,"type":"text","url":""},{"cid":545795,"deleted":false,"image_metadata":{},"is_dz":false,"name":"Bob","permissions":["report"],"pid":113747,"reply_to":-1,"tag":null,"text":"他可能觉得黑龙江跟非洲一样吧","timestamp":1605171118,"type":"text","url":""},{"cid":545796,"deleted":false,"image_metadata":{},"is_dz":false,"name":"Carol","permissions":["report"],"pid":113747,"reply_to":-1,"tag":null,"text":"呜呜呜","timestamp":1605171125,"type":"text","url":""},{"cid":545798,"deleted":false,"image_metadata":{},"is_dz":false,"name":"Dave","permissions":["report"],"pid":113747,"reply_to":-1,"tag":null,"text":"快进到上乎","timestamp":1605171169,"type":"text","url":""},{"cid":545799,"deleted":false,"image_metadata":{},"is_dz":false,"name":"Eve","permissions":["report"],"pid":113747,"reply_to":-1,"tag":null,"text":"曹大佐告诉我们要找到自己心中的非洲","timestamp":1605171198,"type":"text","url":""},{"cid":545800,"deleted":false,"image_metadata":{},"is_dz":false,"name":"Eve","permissions":["report"],"pid":113747,"reply_to":-1,"tag":null,"text":"只要心中有非洲，哪里都是非洲","timestamp":1605171222,"type":"text","url":""},{"cid":545804,"deleted":false,"image_metadata":{},"is_dz":false,"name":"Francis","permissions":["report"],"pid":113747,"reply_to":-1,"tag":null,"text":"黑龙江不正好他老家么","timestamp":1605171330,"type":"text","url":""},{"cid":545824,"deleted":false,"image_metadata":{},"is_dz":false,"name":"Grace","permissions":["report"],"pid":113747,"reply_to":-1,"tag":null,"text":"心中有非洲 哪里都是非洲 建设非洲还用得着跑那么远的地方去吗？\n黑龙江，yyd非洲","timestamp":1605171607,"type":"text","url":""},{"cid":545840,"deleted":false,"image_metadata":{},"is_dz":false,"name":"Hans","permissions":["report"],"pid":113747,"reply_to":-1,"tag":null,"text":"黑龙江多好，低房价低物欲低内卷，资本主义惨淡，人民富豪都不愿意来的地方，可一展大佐宏图也！","timestamp":1605171852,"type":"text","url":""},{"cid":545844,"deleted":false,"image_metadata":{},"is_dz":false,"name":"Isabella","permissions":["report"],"pid":113747,"reply_to":-1,"tag":null,"text":"黑龙江非洲说成立","timestamp":1605171974,"type":"text","url":""},{"cid":545872,"deleted":false,"image_metadata":{},"is_dz":false,"name":"Jason","permissions":["report"],"pid":113747,"reply_to":-1,"tag":null,"text":"黑龙江确实没啥人民富豪，我们坚定不移支持社会主义道路！","timestamp":1605172429,"type":"text","url":""},{"cid":545951,"deleted":false,"image_metadata":{},"is_dz":false,"name":"Kate","permissions":["report"],"pid":113747,"reply_to":-1,"tag":null,"text":"曹大佐早就说了“非洲是每个人自己的精神非洲，不一定非得是地理非洲”，回老家就是大佐的精神非洲呗。。。有啥可喷的","timestamp":1605173987,"type":"text","url":""},{"cid":545997,"deleted":false,"image_metadata":{},"is_dz":false,"name":"Louis","permissions":["report"],"pid":113747,"reply_to":-1,"tag":null,"text":"今年黑龙江政策好？期待一个大佐本人回复","timestamp":1605174905,"type":"text","url":""},{"cid":546559,"deleted":false,"image_metadata":{},"is_dz":false,"name":"Margaret","permissions":["report"],"pid":113747,"reply_to":-1,"tag":null,"text":"是最近的吗？没准是上个学期的呀","timestamp":1605182037,"type":"text","url":""},{"cid":546586,"deleted":false,"image_metadata":{},"is_dz":false,"name":"Nathan","permissions":["report"],"pid":113747,"reply_to":-1,"tag":null,"text":"大佐不是签了国企去非洲当总工吗","timestamp":1605182277,"type":"text","url":""},{"cid":546587,"deleted":false,"image_metadata":{},"is_dz":false,"name":"Olivia","permissions":["report"],"pid":113747,"reply_to":-1,"tag":null,"text":"就事论事，黑龙江选调也挺好的，虽然不喜欢他的一些言论，但是祝福他为东北振兴做出贡献。","timestamp":1605182299,"type":"text","url":""},{"cid":546758,"deleted":false,"image_metadata":{},"is_dz":false,"name":"Paul","permissions":["report"],"pid":113747,"reply_to":-1,"tag":null,"text":"观光团","timestamp":1605183752,"type":"text","url":""},{"cid":546929,"deleted":false,"image_metadata":{},"is_dz":false,"name":"Queen","permissions":["report"],"pid":113747,"reply_to":-1,"tag":null,"text":"曹大佐这是准备去关外物理入关呢","timestamp":1605185836,"type":"text","url":""},{"cid":547384,"deleted":false,"image_metadata":{},"is_dz":false,"name":"Richard","permissions":["report"],"pid":113747,"reply_to":-1,"tag":null,"text":"多少沾点黑","timestamp":1605193440,"type":"text","url":""},{"cid":1028129,"deleted":false,"image_metadata":{},"is_dz":false,"name":"Susan","permissions":["report"],"pid":113747,"reply_to":-1,"tag":null,"text":"黑 非 洲","timestamp":1612136899,"type":"text","url":""},{"cid":1534984,"deleted":false,"image_metadata":{},"is_dz":false,"name":"Thomas","permissions":["report"],"pid":113747,"reply_to":-1,"tag":null,"text":"考古","timestamp":1619427938,"type":"text","url":""},{"cid":3143845,"deleted":false,"image_metadata":{},"is_dz":false,"name":"Uma","permissions":["report"],"pid":113747,"reply_to":-1,"tag":null,"text":"挖一铲子","timestamp":1639214415,"type":"text","url":""}],"post":{"attention":false,"deleted":false,"image_metadata":{},"likenum":29,"permissions":["report","fold"],"pid":113747,"reply":22,"tag":null,"text":"今天去职业发展中心领取盖过章的南方某省份的选调生报名表，在服务台看到了黑龙江选调登记表，竟然有一个熟悉的名字——土木系曹丰泽，瞬间崩塌了，曾经坚定信仰曹学，觉得大佐一定会在毕业季选择去非洲，没想到他竟然报了黑龙江选调生，呜呜呜呜呜呜，为什么啊","timestamp":1605170997,"type":"text","updated_at":1639214415,"url":"","vote":{}}}