{"code":0,"data":[{"cid":548192,"deleted":false,"image_metadata":{},"is_dz":false,"name":"Alice","permissions":["report"],"pid":114225,"reply_to":-1,"tag":null,"text":"羡慕是常情 嫉妒大可不必","timestamp":1605204327,"type":"text","url":""}],"post":{"attention":false,"deleted":false,"image_metadata":{},"likenum":1,"permissions":["report","fold"],"pid":114225,"reply":1,"tag":null,"text":"了解了一下昨天被举报的洞，虽然不至于举报，但是我看到那条洞我也是羡慕嫉妒恨，并且不由得想到未来可能要996修福报才能勉强追上那个dz大学时拥有的幸运，然后越发不爽","timestamp":1605202766,"type":"text","updated_at":1606782643,"url":"","vote":{}}}