{"code":0,"data":[{"cid":548821,"deleted":false,"image_metadata":{},"is_dz":false,"name":"Alice","permissions":["report"],"pid":114403,"reply_to":-1,"tag":null,"text":"日式烤肉：\n鹤一（北大东门），自助烤肉的性价比标杆；可惜北大总店近两年过于火爆，排队是个大问题。\n樱宿烤肉（五道口），去年开的新店，价高量少但是是M9级和牛，味道很不错。\n韩式烤肉：\n坦坦大炉、韩时烤肉，均位于东源大厦，各有特色；个人觉得坦坦大炉量更大些？\n火炉火：没去过，等一个横评\n民族特色烤肉：\n巴依老爷（双清路），除了烤串外还有手抓饭和酸奶","timestamp":1605240123,"type":"text","url":""},{"cid":549141,"deleted":false,"image_metadata":{},"is_dz":true,"name":"洞主","permissions":["report"],"pid":114403,"reply_to":-1,"tag":null,"text":"Re Alice: 谢！！！！！！！！！！！","timestamp":1605244692,"type":"text","url":""}],"post":{"attention":false,"deleted":false,"image_metadata":{},"likenum":13,"permissions":["report","fold"],"pid":114403,"reply":2,"tag":null,"text":"学校附近哪里有比较好吃的烤肉呀？","timestamp":1605239716,"type":"text","updated_at":1606782641,"url":"","vote":{}}}