{"code":0,"data":[{"cid":551369,"deleted":false,"image_metadata":{},"is_dz":false,"name":"Alice","permissions":["report"],"pid":114967,"reply_to":-1,"tag":null,"text":"没有疫情的时候大礼堂每周都有电影的","timestamp":1605279293,"type":"text","url":""},{"cid":551370,"deleted":false,"image_metadata":{},"is_dz":false,"name":"Alice","permissions":["report"],"pid":114967,"reply_to":-1,"tag":null,"text":"现在貌似暂时没有","timestamp":1605279317,"type":"text","url":""},{"cid":552278,"deleted":false,"image_metadata":{},"is_dz":true,"name":"洞主","permissions":["report"],"pid":114967,"reply_to":-1,"tag":null,"text":"好 谢谢！","timestamp":1605313860,"type":"text","url":""}],"post":{"attention":false,"deleted":false,"image_metadata":{},"likenum":2,"permissions":["report","fold"],"pid":114967,"reply":3,"tag":null,"text":"请问清华校内哪里可以看电影呢？","timestamp":1605279173,"type":"text","updated_at":1606782643,"url":"","vote":{}}}