{"code":0,"data":[{"cid":557206,"deleted":false,"image_metadata":{},"is_dz":false,"name":"Alice","permissions":["report"],"pid":116201,"reply_to":-1,"tag":null,"text":"我上过他的实分析，从这门课来看，他比较友善","timestamp":1605424875,"type":"text","url":""},{"cid":557207,"deleted":false,"image_metadata":{},"is_dz":false,"name":"Alice","permissions":["report"],"pid":116201,"reply_to":-1,"tag":null,"text":"抱歉看错了，以为在测评这节课qwq","timestamp":1605424899,"type":"text","url":""},{"cid":558552,"deleted":false,"image_metadata":{},"is_dz":false,"name":"Bob","permissions":["report"],"pid":116201,"reply_to":-1,"tag":null,"text":"微积分 1教205, 时间 32,51","timestamp":1605448452,"type":"text","url":""},{"cid":562491,"deleted":false,"image_metadata":{},"is_dz":true,"name":"洞主","permissions":["report"],"pid":116201,"reply_to":-1,"tag":null,"text":"Re Bob: 谢谢！","timestamp":1605538772,"type":"text","url":""}],"post":{"attention":false,"deleted":false,"image_metadata":{},"likenum":3,"permissions":["report","fold"],"pid":116201,"reply":4,"tag":null,"text":"#112675 捞","timestamp":1605424794,"type":"text","updated_at":1606782642,"url":"","vote":{}}}