{"code":0,"data":[{"cid":562101,"deleted":false,"image_metadata":{},"is_dz":false,"name":"Alice","permissions":["report"],"pid":117262,"reply_to":-1,"tag":null,"text":"我也搜了，一定是同一个，因为跟微信的名字和头像都一样。那个脸真的p的很可怕啊。。迷上她的男孩子都是怎么想的啊","timestamp":1605532442,"type":"text","url":""},{"cid":562108,"deleted":false,"image_metadata":{},"is_dz":true,"name":"洞主","permissions":["report"],"pid":117262,"reply_to":-1,"tag":null,"text":"Re Alice: 我的天呐………","timestamp":1605532632,"type":"text","url":""},{"cid":562110,"deleted":false,"image_metadata":{},"is_dz":false,"name":"Alice","permissions":["report"],"pid":117262,"reply_to":-1,"tag":null,"text":"Re 洞主: 不过身材的确很好，可能是因为这个吧。。","timestamp":1605532687,"type":"text","url":""},{"cid":562123,"deleted":false,"image_metadata":{},"is_dz":true,"name":"洞主","permissions":["report"],"pid":117262,"reply_to":-1,"tag":null,"text":"Re Alice: 这样的身材真的好吗…","timestamp":1605532924,"type":"text","url":""},{"cid":562132,"deleted":false,"image_metadata":{},"is_dz":false,"name":"Alice","permissions":["report"],"pid":117262,"reply_to":-1,"tag":null,"text":"Re 洞主: hhh从cz女生的角度来看，瘦白腿细确实很不错","timestamp":1605533033,"type":"text","url":""},{"cid":562149,"deleted":false,"image_metadata":{},"is_dz":true,"name":"洞主","permissions":["report"],"pid":117262,"reply_to":-1,"tag":null,"text":"Re Alice: 好吧，可能感觉这个有些瘦的夸张了","timestamp":1605533181,"type":"text","url":""},{"cid":562178,"deleted":false,"image_metadata":{},"is_dz":true,"name":"洞主","permissions":["report"],"pid":117262,"reply_to":-1,"tag":null,"text":"不敢新开洞…但私心觉得上一个树洞顶流自然而且好看多了…","timestamp":1605533541,"type":"text","url":""}],"post":{"attention":false,"deleted":false,"image_metadata":{},"likenum":2,"permissions":["report","fold"],"pid":117262,"reply":7,"tag":null,"text":"dana到底啥瓜…\n虽然没有微信，但去微博搜了一下，搜出来的脸简直让人生理不适了…不知道是不是同一个（希望不是）\n","timestamp":1605532337,"type":"text","updated_at":1606782650,"url":"","vote":{}}}