{"code":0,"data":[{"cid":562742,"deleted":false,"image_metadata":{},"is_dz":false,"name":"Alice","permissions":["report"],"pid":117414,"reply_to":-1,"tag":null,"text":"没有","timestamp":1605542016,"type":"text","url":""},{"cid":562744,"deleted":false,"image_metadata":{},"is_dz":false,"name":"Bob","permissions":["report"],"pid":117414,"reply_to":-1,"tag":null,"text":"没有影响","timestamp":1605542027,"type":"text","url":""},{"cid":562750,"deleted":false,"image_metadata":{},"is_dz":false,"name":"Carol","permissions":["report"],"pid":117414,"reply_to":-1,"tag":null,"text":"日经问题","timestamp":1605542108,"type":"text","url":""},{"cid":562752,"deleted":false,"image_metadata":{},"is_dz":true,"name":"洞主","permissions":["report"],"pid":117414,"reply_to":-1,"tag":null,"text":"Re Alice: 谢谢\n","timestamp":1605542132,"type":"text","url":""},{"cid":562754,"deleted":false,"image_metadata":{},"is_dz":true,"name":"洞主","permissions":["report"],"pid":117414,"reply_to":-1,"tag":null,"text":"Re Bob: 谢谢","timestamp":1605542152,"type":"text","url":""},{"cid":563093,"deleted":false,"image_metadata":{},"is_dz":false,"name":"Dave","permissions":["report"],"pid":117414,"reply_to":-1,"tag":null,"text":"没影响 只会显得你wonderful","timestamp":1605546938,"type":"text","url":""}],"post":{"attention":false,"deleted":false,"image_metadata":{},"likenum":2,"permissions":["report","fold"],"pid":117414,"reply":6,"tag":null,"text":"大一萌新求问，记w会有什么影响呢","timestamp":1605542009,"type":"text","updated_at":1606782652,"url":"","vote":{}}}