{"code":0,"data":[{"cid":564017,"deleted":false,"image_metadata":{},"is_dz":false,"name":"Alice","permissions":["report"],"pid":117695,"reply_to":-1,"tag":null,"text":"旋转门不透风 左右滑动进出效率高 至于为什么换来换去我也不知道","timestamp":1605587725,"type":"text","url":""},{"cid":564069,"deleted":false,"image_metadata":{},"is_dz":false,"name":"Bob","permissions":["report"],"pid":117695,"reply_to":-1,"tag":null,"text":"中间？咖啡厅那个吗","timestamp":1605588360,"type":"text","url":""}],"post":{"attention":false,"deleted":false,"image_metadata":{},"likenum":2,"permissions":["report","fold"],"pid":117695,"reply":2,"tag":null,"text":"为什么文图中间那个门有时候是旋转门，有时候是左右滑动来开闭的？","timestamp":1605587575,"type":"text","updated_at":1606782651,"url":"","vote":{}}}