{"code":0,"data":[{"cid":572970,"deleted":false,"image_metadata":{},"is_dz":false,"name":"Alice","permissions":["report"],"pid":118043,"reply_to":-1,"tag":null,"text":"好漂亮！","timestamp":1605712011,"type":"text","url":""}],"post":{"attention":false,"deleted":false,"image_metadata":{},"likenum":1,"permissions":["report","fold"],"pid":118043,"reply":1,"tag":null,"text":"或许在他的眼里，我就像一只浮夸的公鸡，时时抖擞艳丽肤浅的羽毛嚷着嘶哑难听的声响，极力想引起他的注意和兴趣。\n可是内心深处的我啊，就像一只困在梅雨时期潮湿阴暗地窖的蛤蟆，被爱而不得的情绪围攻地喘不过气，连纵身一跃的勇气都提不起来。","timestamp":1605616701,"type":"text","updated_at":1606782653,"url":"","vote":{}}}