{"code":0,"data":[{"cid":568190,"deleted":false,"image_metadata":{},"is_dz":false,"name":"Alice","permissions":["report"],"pid":118493,"reply_to":-1,"tag":null,"text":"蹲","timestamp":1605673021,"type":"text","url":""},{"cid":568208,"deleted":false,"image_metadata":{},"is_dz":false,"name":"Bob","permissions":["report"],"pid":118493,"reply_to":-1,"tag":null,"text":"yysy，无系随机过程今年第一次有期中考试","timestamp":1605673148,"type":"text","url":""},{"cid":568220,"deleted":false,"image_metadata":{},"is_dz":false,"name":"Carol","permissions":["report"],"pid":118493,"reply_to":-1,"tag":null,"text":"无系随机今年第一次考期中吧","timestamp":1605673260,"type":"text","url":""}],"post":{"attention":false,"deleted":false,"image_metadata":{},"likenum":1,"permissions":["report","fold"],"pid":118493,"reply":3,"tag":null,"text":"请问有人有无系概随2的期中往年真题吗 最好有解析的那种 感谢","timestamp":1605672827,"type":"text","updated_at":1606782650,"url":"","vote":{}}}