{"code":0,"data":[{"cid":570985,"deleted":false,"image_metadata":{},"is_dz":false,"name":"Alice","permissions":["report"],"pid":119079,"reply_to":-1,"tag":null,"text":"又来了","timestamp":1605698479,"type":"text","url":""},{"cid":570997,"deleted":false,"image_metadata":{},"is_dz":false,"name":"Bob","permissions":["report"],"pid":119079,"reply_to":-1,"tag":null,"text":"傻逼","timestamp":1605698547,"type":"text","url":""},{"cid":571030,"deleted":false,"image_metadata":{},"is_dz":false,"name":"Carol","permissions":["report"],"pid":119079,"reply_to":-1,"tag":null,"text":"Re : （考上清华）∧（具备这样的逻辑思维）∧（没有该有的辨事能力）→（更大的概率是______院人）","timestamp":1605698655,"type":"text","url":""},{"cid":571044,"deleted":false,"image_metadata":{},"is_dz":false,"name":"Dave","permissions":["report"],"pid":119079,"reply_to":-1,"tag":null,"text":"倒也不是概率问题，就是美院的，知道的人不少","timestamp":1605698703,"type":"text","url":""},{"cid":571069,"deleted":false,"image_metadata":{},"is_dz":true,"name":"洞主","permissions":["report"],"pid":119079,"reply_to":-1,"tag":null,"text":"Re Dave: 我指的是#119007的Alice。\n可别乱说是哪个院哈。\n我怕被任何一个院的人做成海报。\n","timestamp":1605698829,"type":"text","url":""}],"post":{"attention":false,"deleted":false,"image_metadata":{},"likenum":1,"permissions":["report","fold"],"pid":119079,"reply":5,"tag":null,"text":"#119007\n（没有人出来告诉大家这个女的究竟是谁）→（这个女的正直）\n（考上清华）∧（具备这样的逻辑思维）→（更大的概率是______院人）\n\n洞友们们自行填空","timestamp":1605698445,"type":"text","updated_at":1606782651,"url":"","vote":{}}}