{"code":0,"data":[{"cid":576910,"deleted":false,"image_metadata":{},"is_dz":false,"name":"Alice","permissions":["report"],"pid":120215,"reply_to":-1,"tag":null,"text":"不是立案登记制了吗（？）","timestamp":1605765804,"type":"text","url":""},{"cid":576922,"deleted":false,"image_metadata":{},"is_dz":false,"name":"Bob","permissions":["report"],"pid":120215,"reply_to":-1,"tag":null,"text":"登记制度额然后呢","timestamp":1605765936,"type":"text","url":""},{"cid":576924,"deleted":false,"image_metadata":{},"is_dz":true,"name":"洞主","permissions":["report"],"pid":120215,"reply_to":-1,"tag":null,"text":"Re Alice: 刑事案件立案登记。。。。。","timestamp":1605765963,"type":"text","url":""},{"cid":576928,"deleted":false,"image_metadata":{},"is_dz":false,"name":"Alice","permissions":["report"],"pid":120215,"reply_to":-1,"tag":null,"text":"Re Bob: 凭立案回执就可以吓唬学姐和学校了吧，当然如果有传票、判决书那肯定威力更大","timestamp":1605766008,"type":"text","url":""},{"cid":576945,"deleted":false,"image_metadata":{},"is_dz":false,"name":"Alice","permissions":["report"],"pid":120215,"reply_to":-1,"tag":null,"text":"Re 洞主: 刑事自诉是适用立案登记制的吧。。难道我看的是假的文件","timestamp":1605766186,"type":"text","url":""},{"cid":579428,"deleted":false,"image_metadata":{},"is_dz":true,"name":"洞主","permissions":["report"],"pid":120215,"reply_to":-1,"tag":null,"text":"Re Alice: 是这样没错，但你要考虑现在年底法院忙的一笔。。。。。。。这种小事真不会立案的","timestamp":1605786903,"type":"text","url":""}],"post":{"attention":false,"deleted":false,"image_metadata":{},"likenum":2,"permissions":["report","fold"],"pid":120215,"reply":6,"tag":null,"text":"让学弟去法院自诉的。。。。。这种案子怎么可能会刑事立案，明显是情节轻微不构成犯罪呀。\n再说，去海淀法院好麻烦 我校五金后面就是东升法院，去立案 （民事侵权）然后拿通知书去和辅导员说，不处分那个学姐就不撤诉：）哈哈哈哈哈，学校说不处分学姐我就申请网上直播公开审理 哈哈哈哈哈哈","timestamp":1605765654,"type":"text","updated_at":1606782653,"url":"","vote":{}}}