{"code":0,"data":[{"cid":580511,"deleted":false,"image_metadata":{"h":2202,"w":1820},"is_dz":true,"name":"洞主","permissions":["report"],"pid":120800,"reply_to":-1,"tag":null,"text":"","timestamp":1605793295,"type":"image","url":"de/dejmtn6cy5c5beurqm2moz3jsvlsgszg.jpeg"}],"post":{"attention":false,"deleted":false,"image_metadata":{"h":1025,"w":848},"likenum":1,"permissions":["report","fold"],"pid":120800,"reply":1,"tag":"NSFW","text":"#NSFW","timestamp":1605790996,"type":"image","updated_at":1606782652,"url":"az/aze4kidzjglw2krvshu3q4prcqqgoui2.jpeg","vote":{}}}