{"code":0,"data":[{"cid":585625,"deleted":false,"image_metadata":{},"is_dz":false,"name":"Alice","permissions":["report"],"pid":121877,"reply_to":-1,"tag":null,"text":"嫦娥工程万岁 好耶","timestamp":1605843503,"type":"text","url":""},{"cid":585628,"deleted":false,"image_metadata":{},"is_dz":false,"name":"Bob","permissions":["report"],"pid":121877,"reply_to":-1,"tag":null,"text":"恭喜我世一大喜提热搜。\n是美院啊，那打扰了，告辞","timestamp":1605843518,"type":"text","url":""},{"cid":585652,"deleted":false,"image_metadata":{},"is_dz":true,"name":"洞主","permissions":["report"],"pid":121877,"reply_to":-1,"tag":null,"text":"这样上热搜第一确实不太好","timestamp":1605843614,"type":"text","url":""}],"post":{"attention":false,"deleted":false,"image_metadata":{"h":1792,"w":828},"likenum":3,"permissions":["report","fold"],"pid":121877,"reply":3,"tag":null,"text":"啊这","timestamp":1605843473,"type":"image","updated_at":1606782654,"url":"ly/lyubhfzujfveqj6lejxklxgzzx3wtrny.jpeg","vote":{}}}