{"code":0,"data":[{"cid":585670,"deleted":false,"image_metadata":{},"is_dz":true,"name":"洞主","permissions":["report"],"pid":121885,"reply_to":-1,"tag":null,"text":"清华还有不少人支持以牙还牙同态复仇，我是没想到的","timestamp":1605843713,"type":"text","url":""},{"cid":585673,"deleted":false,"image_metadata":{},"is_dz":false,"name":"Alice","permissions":["report"],"pid":121885,"reply_to":-1,"tag":null,"text":"何以报德？","timestamp":1605843719,"type":"text","url":""},{"cid":585674,"deleted":false,"image_metadata":{},"is_dz":false,"name":"Bob","permissions":["report"],"pid":121885,"reply_to":-1,"tag":null,"text":"支持","timestamp":1605843719,"type":"text","url":""},{"cid":585676,"deleted":false,"image_metadata":{},"is_dz":false,"name":"Alice","permissions":["report"],"pid":121885,"reply_to":-1,"tag":null,"text":"Re 洞主: 不是以牙还牙，是十倍奉还","timestamp":1605843742,"type":"text","url":""},{"cid":585677,"deleted":false,"image_metadata":{},"is_dz":false,"name":"Carol","permissions":["report"],"pid":121885,"reply_to":-1,"tag":null,"text":"Re 洞主: 真就快退到原始人","timestamp":1605843748,"type":"text","url":""},{"cid":585679,"deleted":false,"image_metadata":{},"is_dz":false,"name":"Dave","permissions":["report"],"pid":121885,"reply_to":-1,"tag":null,"text":"支持，dz顶住","timestamp":1605843761,"type":"text","url":""},{"cid":585683,"deleted":false,"image_metadata":{},"is_dz":false,"name":"Eve","permissions":["report"],"pid":121885,"reply_to":-1,"tag":null,"text":"以德报怨何以报德","timestamp":1605843785,"type":"text","url":""},{"cid":585689,"deleted":false,"image_metadata":{},"is_dz":false,"name":"Carol","permissions":["report"],"pid":121885,"reply_to":-1,"tag":null,"text":"Re Eve: 都说了是以直报怨","timestamp":1605843828,"type":"text","url":""},{"cid":585692,"deleted":false,"image_metadata":{},"is_dz":true,"name":"洞主","permissions":["report"],"pid":121885,"reply_to":-1,"tag":null,"text":"Re Alice: 以直报怨，以德报德","timestamp":1605843848,"type":"text","url":""},{"cid":585701,"deleted":false,"image_metadata":{},"is_dz":false,"name":"Francis","permissions":["report"],"pid":121885,"reply_to":-1,"tag":null,"text":"支持dz","timestamp":1605843880,"type":"text","url":""},{"cid":585706,"deleted":false,"image_metadata":{},"is_dz":false,"name":"Grace","permissions":["report"],"pid":121885,"reply_to":-1,"tag":null,"text":"Re Eve: 读一下《论语》吧","timestamp":1605843907,"type":"text","url":""},{"cid":585713,"deleted":false,"image_metadata":{},"is_dz":false,"name":"Hans","permissions":["report"],"pid":121885,"reply_to":-1,"tag":null,"text":"Re 洞主: 难道不应该支持以牙还牙吗","timestamp":1605843969,"type":"text","url":""},{"cid":585718,"deleted":false,"image_metadata":{},"is_dz":true,"name":"洞主","permissions":["report"],"pid":121885,"reply_to":-1,"tag":null,"text":"Re Eve: 闭目塞听，固执己见，不是理性和学习的态度","timestamp":1605843990,"type":"text","url":""},{"cid":585730,"deleted":false,"image_metadata":{},"is_dz":true,"name":"洞主","permissions":["report"],"pid":121885,"reply_to":-1,"tag":null,"text":"Re Hans: 您的思想可以说单纯幼稚了","timestamp":1605844038,"type":"text","url":""},{"cid":585740,"deleted":false,"image_metadata":{},"is_dz":false,"name":"Isabella","permissions":["report"],"pid":121885,"reply_to":-1,"tag":null,"text":"那什么叫直呢？","timestamp":1605844065,"type":"text","url":""},{"cid":585750,"deleted":false,"image_metadata":{},"is_dz":false,"name":"Dave","permissions":["report"],"pid":121885,"reply_to":-1,"tag":null,"text":"Re Isabella: 建议重读这个洞再来发言","timestamp":1605844105,"type":"text","url":""},{"cid":585765,"deleted":false,"image_metadata":{},"is_dz":true,"name":"洞主","permissions":["report"],"pid":121885,"reply_to":-1,"tag":null,"text":"Re Isabella: 说了半天，您还没理解吗？","timestamp":1605844196,"type":"text","url":""},{"cid":585769,"deleted":false,"image_metadata":{},"is_dz":false,"name":"Jason","permissions":["report"],"pid":121885,"reply_to":-1,"tag":null,"text":"可能我不文明吧，我还是认为应该以牙还牙，杀人偿命。每每想到被杀者的凄惨之状，和现在所谓文明下杀人犯的合理要求得到满足我就觉得荒谬。被杀者死的时候没有得到人道的关怀，杀人犯连判个死刑都要磨磨唧唧半天，最后还有一顿好饭可吃，还有遗愿可以跟家人说。如果伦理的当然态度或者文明是这种保护施害者以保证人道主义的实现的话那我确实不文明","timestamp":1605844209,"type":"text","url":""},{"cid":585771,"deleted":false,"image_metadata":{},"is_dz":false,"name":"Kate","permissions":["report"],"pid":121885,"reply_to":-1,"tag":null,"text":"请dz表演一个合适的惩罚","timestamp":1605844217,"type":"text","url":""},{"cid":585805,"deleted":false,"image_metadata":{},"is_dz":false,"name":"Louis","permissions":["report"],"pid":121885,"reply_to":-1,"tag":null,"text":"那什么是“适当”的惩罚呢？不会是pyq道个歉就完事了吧，不会吧不会吧","timestamp":1605844395,"type":"text","url":""},{"cid":585913,"deleted":false,"image_metadata":{},"is_dz":false,"name":"Margaret","permissions":["report"],"pid":121885,"reply_to":-1,"tag":null,"text":"对等,reciprocal:  given, felt, or done in return.\n这是不同利益双方谈判合作交流的基础，\n这和刑罚论中的同态复仇纯粹是两种东西，不要鸡同鸭讲。\n考虑下道歉，各类法院判例中，公开道歉是要登报的，树洞也算公开道歉吗","timestamp":1605844919,"type":"text","url":""},{"cid":585964,"deleted":false,"image_metadata":{},"is_dz":false,"name":"Nathan","permissions":["report"],"pid":121885,"reply_to":-1,"tag":null,"text":"Re Alice: 半泽？应该百倍奉还了哈哈","timestamp":1605845165,"type":"text","url":""},{"cid":586141,"deleted":false,"image_metadata":{},"is_dz":false,"name":"Olivia","permissions":["report"],"pid":121885,"reply_to":-1,"tag":null,"text":"Re : 说的好棒","timestamp":1605846238,"type":"text","url":""}],"post":{"attention":false,"deleted":false,"image_metadata":{},"likenum":15,"permissions":["report","fold"],"pid":121885,"reply":23,"tag":null,"text":"以直报怨: 能自制地压制住怨恨的感情，不让其左右自己的判断，理智决策，追加适当的惩罚。“适当的”不是“等价的、等值的”，历史上“以牙还牙，杀人偿命”属于等值理解。然而，人类社会的发展不是重复零和的过程，而是一个善长恶消的过程，抑恶扬善才是伦理的当然态度。","timestamp":1605843633,"type":"text","updated_at":1606782653,"url":"","vote":{}}}