{"code":0,"data":[{"cid":592544,"deleted":false,"image_metadata":{},"is_dz":false,"name":"Alice","permissions":["report"],"pid":123085,"reply_to":-1,"tag":null,"text":"这种事情拜托不要说出来。会让我们没有暧昧对象的人很尴尬、想放火。","timestamp":1605928423,"type":"text","url":""},{"cid":592546,"deleted":false,"image_metadata":{},"is_dz":true,"name":"洞主","permissions":["report"],"pid":123085,"reply_to":-1,"tag":null,"text":"Re Alice: 那你去发展，很容易","timestamp":1605928449,"type":"text","url":""},{"cid":592561,"deleted":false,"image_metadata":{},"is_dz":false,"name":"Bob","permissions":["report"],"pid":123085,"reply_to":-1,"tag":null,"text":"Re 洞主: 怎么发展呢 Bob连怎么和喜欢的xjj说上话都不知道","timestamp":1605928592,"type":"text","url":""},{"cid":592569,"deleted":false,"image_metadata":{},"is_dz":false,"name":"Carol","permissions":["report"],"pid":123085,"reply_to":-1,"tag":null,"text":"Re Bob: Carol找喜欢的xjj说话人家都无视我了","timestamp":1605928686,"type":"text","url":""},{"cid":592742,"deleted":false,"image_metadata":{},"is_dz":false,"name":"Dave","permissions":["report"],"pid":123085,"reply_to":-1,"tag":null,"text":"Re Carol: Dave身边连xjj都没有","timestamp":1605931081,"type":"text","url":""},{"cid":592768,"deleted":false,"image_metadata":{},"is_dz":false,"name":"Carol","permissions":["report"],"pid":123085,"reply_to":-1,"tag":null,"text":"Re Dave: 感觉没有总比被无视好吧...55","timestamp":1605931523,"type":"text","url":""}],"post":{"attention":false,"deleted":false,"image_metadata":{},"likenum":4,"permissions":["report","fold"],"pid":123085,"reply":6,"tag":null,"text":"为什么和很多人暧昧就算是海王呢，我一直以为在没确定关系之前是可以多线发展的，这样效率高一点，一个一个发展万亿不成功就很耽误时间啊。当然我是会和对方说清楚的。有时候也不会明说，但是也会发现对方也在养的样子（一边和我暧昧一边会跟我说今天身边的哪个女生很性感啥的）。总之我是觉得进入关系之后才会有忠诚方面的约束","timestamp":1605928019,"type":"text","updated_at":1606782653,"url":"","vote":{}}}