{"code":0,"data":[{"cid":596481,"deleted":false,"image_metadata":{},"is_dz":false,"name":"Alice","permissions":["report"],"pid":123899,"reply_to":-1,"tag":null,"text":"蹭蹭?","timestamp":1605977066,"type":"text","url":""},{"cid":596494,"deleted":false,"image_metadata":{},"is_dz":true,"name":"洞主","permissions":["report"],"pid":123899,"reply_to":-1,"tag":null,"text":"天真无邪啊！","timestamp":1605977189,"type":"text","url":""},{"cid":596500,"deleted":false,"image_metadata":{},"is_dz":false,"name":"Alice","permissions":["report"],"pid":123899,"reply_to":-1,"tag":null,"text":"Re 洞主: ♂可以吗","timestamp":1605977232,"type":"text","url":""},{"cid":596510,"deleted":false,"image_metadata":{},"is_dz":false,"name":"Bob","permissions":["report"],"pid":123899,"reply_to":-1,"tag":null,"text":"找♂♀？","timestamp":1605977315,"type":"text","url":""},{"cid":596511,"deleted":false,"image_metadata":{},"is_dz":true,"name":"洞主","permissions":["report"],"pid":123899,"reply_to":-1,"tag":null,"text":"hhhh没恶意就行","timestamp":1605977316,"type":"text","url":""},{"cid":596528,"deleted":false,"image_metadata":{},"is_dz":true,"name":"洞主","permissions":["report"],"pid":123899,"reply_to":-1,"tag":null,"text":"孤单一人感觉挺那啥的","timestamp":1605977448,"type":"text","url":""},{"cid":596536,"deleted":false,"image_metadata":{},"is_dz":false,"name":"Carol","permissions":["report"],"pid":123899,"reply_to":-1,"tag":null,"text":"怎么相伴一晚啊","timestamp":1605977511,"type":"text","url":""},{"cid":596563,"deleted":false,"image_metadata":{},"is_dz":false,"name":"Dave","permissions":["report"],"pid":123899,"reply_to":-1,"tag":null,"text":"好恶心","timestamp":1605977765,"type":"text","url":""},{"cid":596649,"deleted":false,"image_metadata":{},"is_dz":false,"name":"Eve","permissions":["report"],"pid":123899,"reply_to":-1,"tag":null,"text":"马上就被截屏流出了啊","timestamp":1605978601,"type":"text","url":""}],"post":{"attention":false,"deleted":false,"image_metadata":{},"likenum":5,"permissions":["report","fold"],"pid":123899,"reply":9,"tag":null,"text":"有人想要相伴一晚睡觉的吗（♂）","timestamp":1605977046,"type":"text","updated_at":1606782654,"url":"","vote":{}}}