{"code":0,"data":[{"cid":608844,"deleted":false,"image_metadata":{},"is_dz":true,"name":"洞主","permissions":["report"],"pid":126315,"reply_to":-1,"tag":null,"text":"不喜欢北美的硬摇滚和垃圾摇滚，但是很喜欢北美的Folk以及民谣歌曲。这个乐队挺有趣的，歌曲很灵动，编曲也很不拘一格","timestamp":1606229265,"type":"text","url":""},{"cid":608909,"deleted":false,"image_metadata":{},"is_dz":false,"name":"Alice","permissions":["report"],"pid":126315,"reply_to":-1,"tag":null,"text":"您是lxm吗(ﾟOﾟ)","timestamp":1606230232,"type":"text","url":""},{"cid":608937,"deleted":false,"image_metadata":{},"is_dz":true,"name":"洞主","permissions":["report"],"pid":126315,"reply_to":-1,"tag":null,"text":"Re Alice: 如果是人名缩写的话并不是","timestamp":1606230564,"type":"text","url":""},{"cid":608962,"deleted":false,"image_metadata":{},"is_dz":false,"name":"Bob","permissions":["report"],"pid":126315,"reply_to":-1,"tag":null,"text":"Re 洞主:  我大概猜到Alice说的是谁了，我现实中一个爱英摇爱后朋对新浪潮电子感觉一般般的朋友","timestamp":1606230855,"type":"text","url":""},{"cid":609001,"deleted":false,"image_metadata":{},"is_dz":true,"name":"洞主","permissions":["report"],"pid":126315,"reply_to":-1,"tag":null,"text":"Re Bob: 这种问题微信问感觉更直接","timestamp":1606231392,"type":"text","url":""}],"post":{"attention":false,"deleted":false,"image_metadata":{"h":1400,"w":1400},"likenum":4,"permissions":["report","fold"],"pid":126315,"reply":5,"tag":null,"text":"#125432\nRock music\u0026Indie music\n今日份安利：In The Aeroplane Over The Sea by Neutral Milk Hotel","timestamp":1606229093,"type":"image","updated_at":1606782656,"url":"db/dbs45bikgqfkg72rdsuacjzvtcreqcuu.jpeg","vote":{}}}