{"code":0,"data":[{"cid":610431,"deleted":false,"image_metadata":{},"is_dz":true,"name":"洞主","permissions":["report"],"pid":126619,"reply_to":-1,"tag":null,"text":"不发","timestamp":1606271043,"type":"text","url":""},{"cid":610432,"deleted":false,"image_metadata":{},"is_dz":false,"name":"Alice","permissions":["report"],"pid":126619,"reply_to":-1,"tag":null,"text":"这么惨的吗","timestamp":1606271061,"type":"text","url":""},{"cid":611574,"deleted":false,"image_metadata":{},"is_dz":false,"name":"Bob","permissions":["report"],"pid":126619,"reply_to":-1,"tag":null,"text":"Re 洞主: 学校的肯定不发啦","timestamp":1606285765,"type":"text","url":""}],"post":{"attention":false,"deleted":false,"image_metadata":{},"likenum":2,"permissions":["report","fold"],"pid":126619,"reply":3,"tag":null,"text":"延期的老博士学校补发工资了是吗？看到账户余额真是感觉过不下去了","timestamp":1606271025,"type":"text","updated_at":1606782654,"url":"","vote":{}}}