{"code":0,"data":[{"cid":611154,"deleted":false,"image_metadata":{},"is_dz":true,"name":"洞主","permissions":["report"],"pid":126748,"reply_to":-1,"tag":null,"text":"如果退课的话又要加一个w，但是近期的压力来源完全就是这门课了quq","timestamp":1606279934,"type":"text","url":""},{"cid":611160,"deleted":false,"image_metadata":{},"is_dz":true,"name":"洞主","permissions":["report"],"pid":126748,"reply_to":-1,"tag":null,"text":"npy也一天没回我消息…好担心，好丧(ಥ_ಥ)","timestamp":1606279995,"type":"text","url":""},{"cid":611261,"deleted":false,"image_metadata":{},"is_dz":false,"name":"Alice","permissions":["report"],"pid":126748,"reply_to":-1,"tag":null,"text":"不清楚这门课给分，但别的课给分很好（尽可能地好了），老师人也特别特别好","timestamp":1606280884,"type":"text","url":""},{"cid":612143,"deleted":false,"image_metadata":{},"is_dz":false,"name":"Bob","permissions":["report"],"pid":126748,"reply_to":-1,"tag":null,"text":"Re Alice: yysy经管的课没什么给分好坏之别吧 所有课卡30%优秀率 老师也基本都靠调正态","timestamp":1606294854,"type":"text","url":""},{"cid":612196,"deleted":false,"image_metadata":{},"is_dz":false,"name":"Carol","permissions":["report"],"pid":126748,"reply_to":-1,"tag":null,"text":"Re Bob: 中微给33%优秀","timestamp":1606295583,"type":"text","url":""},{"cid":613945,"deleted":false,"image_metadata":{},"is_dz":true,"name":"洞主","permissions":["report"],"pid":126748,"reply_to":-1,"tag":null,"text":"Re Alice: 谢谢您！决定还是努力学下去w","timestamp":1606319374,"type":"text","url":""}],"post":{"attention":false,"deleted":false,"image_metadata":{},"likenum":1,"permissions":["report","fold"],"pid":126748,"reply":6,"tag":null,"text":"想问问zj老师的行为经济学给分怎么样quq非经管同学也没有认识的人，第一次作业拿到的分也好低，害怕了，真的有点学不下去","timestamp":1606279892,"type":"text","updated_at":1606782653,"url":"","vote":{}}}