{"code":0,"data":[{"cid":611740,"deleted":false,"image_metadata":{},"is_dz":false,"name":"Alice","permissions":["report"],"pid":126832,"reply_to":-1,"tag":null,"text":"rape me","timestamp":1606288288,"type":"text","url":""},{"cid":611742,"deleted":false,"image_metadata":{},"is_dz":false,"name":"Alice","permissions":["report"],"pid":126832,"reply_to":-1,"tag":null,"text":"rape me again","timestamp":1606288301,"type":"text","url":""},{"cid":611817,"deleted":false,"image_metadata":{},"is_dz":false,"name":"Bob","permissions":["report"],"pid":126832,"reply_to":-1,"tag":null,"text":"喜欢他们那首season in the sun","timestamp":1606289501,"type":"text","url":""}],"post":{"attention":false,"deleted":false,"image_metadata":{"h":699,"w":1465},"likenum":2,"permissions":["report","fold"],"pid":126832,"reply":3,"tag":null,"text":"有喜欢Nirvana的吗","timestamp":1606285938,"type":"image","updated_at":1606782653,"url":"bu/bu6vldhyf2bca2vcvsyhxuycaeviuhal.jpeg","vote":{}}}