{"code":0,"data":[{"cid":613340,"deleted":false,"image_metadata":{},"is_dz":false,"name":"Alice","permissions":["report"],"pid":127125,"reply_to":-1,"tag":null,"text":"哭出来呀，为什么不呢，在一个没有人会发现的地方","timestamp":1606310503,"type":"text","url":""},{"cid":614311,"deleted":false,"image_metadata":{},"is_dz":true,"name":"洞主","permissions":["report"],"pid":127125,"reply_to":-1,"tag":null,"text":"Re Alice: hhh，焦虑卡住了我的喉咙\n我，连哭都哭不出","timestamp":1606322822,"type":"text","url":""}],"post":{"attention":false,"deleted":false,"image_metadata":{},"likenum":0,"permissions":["report","fold"],"pid":127125,"reply":2,"tag":null,"text":"终于知道什么叫做窒息的感觉了，\n哭不出来，肺部肌肉紧张自然就感觉了","timestamp":1606309339,"type":"text","updated_at":1606782653,"url":"","vote":{}}}