{"code":0,"data":[{"cid":614045,"deleted":false,"image_metadata":{},"is_dz":false,"name":"Alice","permissions":["report"],"pid":127273,"reply_to":-1,"tag":null,"text":"来啦！","timestamp":1606320302,"type":"text","url":""},{"cid":614048,"deleted":false,"image_metadata":{},"is_dz":false,"name":"Alice","permissions":["report"],"pid":127273,"reply_to":-1,"tag":null,"text":"晚安洞洞！","timestamp":1606320313,"type":"text","url":""},{"cid":615404,"deleted":false,"image_metadata":{},"is_dz":true,"name":"洞主","permissions":["report"],"pid":127273,"reply_to":-1,"tag":null,"text":"Re Alice: 中午好Alice～","timestamp":1606364324,"type":"text","url":""}],"post":{"attention":false,"deleted":false,"image_metadata":{"h":1607,"w":1080},"likenum":2,"permissions":["report","fold"],"pid":127273,"reply":3,"tag":null,"text":"#魔法鱼零点电台 Day23\n《IDK》-Mosss\n“朝着你，靠近，坠入，沉溺。”\n晚安。","timestamp":1606319154,"type":"image","updated_at":1606782653,"url":"sx/sx35szunvshdm5etn4e3q7uhyryf6qan.jpeg","vote":{}}}